elkoep_lara/__init__.py
elkoep_lara-0.2.1.dist-info/LICENSE
elkoep_lara-0.2.1.dist-info/METADATA
elkoep_lara-0.2.1.dist-info/WHEEL
elkoep_lara-0.2.1.dist-info/top_level.txt
elkoep_lara-0.2.1.dist-info/RECORD
