Metadata-Version: 2.1
Name: elkoep-lara
Version: 0.2.1
Summary: Python API for controlling ElkoEP Lara devices
Home-page: https://github.com/exKAjFASH/
Author: Vyacheslav Anisimov
Author-email: kajfash@lycos.com
License: UNKNOWN
Platform: UNKNOWN
Classifier: Development Status :: 4 - Beta
Classifier: Intended Audience :: Developers
Classifier: License :: OSI Approved :: MIT License
Classifier: Operating System :: OS Independent
Classifier: Programming Language :: Python
